{
  "id": "@hf/thebloke/zephyr-7b-beta-awq",
  "name": "zephyr-7b-beta-awq",
  "created_by": "thebloke",
  "source": "official",
  "last_updated": "2026-03-23",
  "capabilities": {
    "streaming": true
  },
  "_generated": {
    "name": "b10fa2b3",
    "capabilities": "0fa77dc6",
    "parameters": "8f14e45f",
    "status": "127aecde",
    "model_type": "d669f408",
    "page_url": "d74633a5",
    "modalities": "68e53d93"
  },
  "parameters": 7,
  "status": "preview",
  "model_type": "chat",
  "page_url": "https://developers.cloudflare.com/workers-ai/models/#zephyr-7b-beta-awq",
  "modalities": {
    "input": ["text"],
    "output": ["text"]
  }
}
