{
  "id": "fireworks/llama-v3p1-70b-instruct",
  "name": "llama-v3p1-70b-instruct",
  "created_by": "meta",
  "source": "official",
  "last_updated": "2026-03-23",
  "context_window": 131100,
  "capabilities": {
    "streaming": true
  },
  "pricing": {
    "input": 0.9,
    "output": 1,
    "cached_input": 1
  },
  "_generated": {
    "name": "780a9cbe",
    "context_window": "a683b9ae",
    "capabilities": "0fa77dc6",
    "pricing": "d5937f56",
    "model_type": "d669f408",
    "parameters": "7cbbc409",
    "page_url": "b8344b30"
  },
  "model_type": "chat",
  "parameters": 70,
  "page_url": "https://fireworks.ai/models/fireworks/llama-v3p1-70b-instruct"
}
