{
  "id": "fireworks/phind-code-llama-34b-v1",
  "name": "phind-code-llama-34b-v1",
  "created_by": "meta",
  "source": "official",
  "last_updated": "2026-03-23",
  "context_window": 16400,
  "capabilities": {
    "streaming": true
  },
  "pricing": {
    "input": 1,
    "output": 1,
    "cached_input": 1
  },
  "_generated": {
    "name": "2269d4b5",
    "context_window": "e375a58e",
    "capabilities": "0fa77dc6",
    "pricing": "cb03f68e",
    "parameters": "e369853d",
    "page_url": "b3fd18da"
  },
  "parameters": 34,
  "page_url": "https://fireworks.ai/models/fireworks/phind-code-llama-34b-v1"
}
