{
  "id": "canopylabs/orpheus-v1-english",
  "name": "Canopy Labs Orpheus V1 English",
  "created_by": "canopy-labs",
  "source": "official",
  "last_updated": "2026-03-21",
  "status": "preview",
  "context_window": 4000,
  "max_output_tokens": 50000,
  "model_type": "tts",
  "modalities": {
    "input": ["text"],
    "output": ["audio"]
  },
  "_generated": {
    "name": "0fba1fc6",
    "status": "127aecde",
    "model_type": "4e16a2cf",
    "context_window": "1bd69c7d",
    "max_output_tokens": "1017bfd4",
    "modalities": "601e776d"
  }
}
