{
  "id": "embed-multilingual-v3.0",
  "name": "embed-multilingual-v3.0",
  "created_by": "cohere",
  "source": "official",
  "last_updated": "2026-03-26",
  "description": "Provides multilingual classification and embedding support. See supported languages here.",
  "status": "active",
  "context_window": 512,
  "model_type": "embed",
  "tagline": "Text, Images",
  "capabilities": {
    "streaming": true,
    "vision": true
  },
  "modalities": {
    "input": ["text"],
    "output": ["text"]
  },
  "endpoints": ["embed"],
  "_generated": {
    "name": "37901230",
    "description": "05feada6",
    "status": "379ac110",
    "context_window": "10a7cdd9",
    "model_type": "764cb3de",
    "tagline": "67bf8dfd",
    "capabilities": "8a3b232e",
    "modalities": "68e53d93",
    "endpoints": "9f6acf8c",
    "family": "764cb3de",
    "license": "9186c466",
    "open_weight": "68934a3e",
    "page_url": "1ddcfa00"
  },
  "family": "embed",
  "license": "proprietary",
  "open_weight": false,
  "page_url": "https://docs.cohere.com/docs/models#embed-multilingual-v3.0"
}
