{
  "id": "huggingface/zai-org/GLM-5",
  "name": "HuggingFace: zai-org/GLM-5",
  "created_by": "huggingface",
  "source": "official",
  "last_updated": "2026-03-24",
  "pricing": {
    "input": 1,
    "output": 3.1999999999999997
  },
  "_generated": {
    "name": "2d67d0f6",
    "pricing": "a20f6b46",
    "family": "bfb92394",
    "model_type": "d669f408",
    "modalities": "68e53d93"
  },
  "family": "GLM-5",
  "model_type": "chat",
  "modalities": {
    "input": ["text"],
    "output": ["text"]
  }
}
